tiv/__init__.py
tiv/__main__.py
tiv-0.2.0.dist-info/DESCRIPTION.rst
tiv-0.2.0.dist-info/METADATA
tiv-0.2.0.dist-info/RECORD
tiv-0.2.0.dist-info/WHEEL
tiv-0.2.0.dist-info/entry_points.txt
tiv-0.2.0.dist-info/metadata.json
tiv-0.2.0.dist-info/top_level.txt
