Metadata-Version: 2.0
Name: tiv
Version: 0.2.0
Summary: Terminal Image Viewer
Home-page: https://gitlab.com/nul.one/tiv
Author: Predrag Mandic
Author-email: info@nul.one
License: BSD
Download-URL: https://gitlab.com/nul.one/tiv/-/archive/0.2.0/tiv-0.2.0.tar.gz
Platform: UNKNOWN
Requires-Python: >=3.4.6
Requires-Dist: Pillow (>=3.1.2,<4.0)
Requires-Dist: cairosvg (>=2.2.1,<2.3)
Requires-Dist: click (>=6.7.0,<8.0)
Requires-Dist: numpy (>=1.15.1,<2.0)
